{
    "powers": [
        "origins:water_breathing",
        "merling:wet_eyes",
        "merling:aqua_affinity",
        "merling:swim_speed",
		"merling:air_from_potions/air_from_potions_2",
        "origins:like_water",
        "merling:aquatic",
        "origins:conduit_power_on_land"
    ],
	"icon": "minecraft:cod",
	"order": 0,
	"impact": 3,
	"name": "Name",
	"description": "Description.",
	"unchoosable": true,
	"upgrades": [
		{
			"condition": "minecraft:adventure/kill_all_mobs",
			"origin": "merling:upgraded2",
			"announcement": "You have evolved into a Name. You are now at the pinnacle of your Origin."
		}
	]
}